dsfun/__init__.py
dsfun/functions.py
tests/__init__.py
tests/test_functions.py
dsfun-0.0.4.dist-info/LICENSE
dsfun-0.0.4.dist-info/METADATA
dsfun-0.0.4.dist-info/WHEEL
dsfun-0.0.4.dist-info/top_level.txt
dsfun-0.0.4.dist-info/RECORD
