Metadata-Version: 2.1
Name: dsfun
Version: 0.0.4
Summary: Helpful functions for Data Science
Home-page: https://github.com/DawidDabkowski/dsfun
Author: Dawid Dabkowski
Author-email: dav.dabkowski@gmail.com
License: UNKNOWN
Platform: UNKNOWN
Classifier: Programming Language :: Python :: 3
Classifier: License :: OSI Approved :: MIT License
Classifier: Operating System :: OS Independent
Requires-Python: >=3.8
Requires-Dist: tensorflow (>=2.2.0)
Requires-Dist: pytest (>=5.4.2)
Provides-Extra: developing
Requires-Dist: twine (>=3.1.1) ; extra == 'developing'
Requires-Dist: jupyterlab (>=2.1.3) ; extra == 'developing'
Requires-Dist: ipdb (>=0.13.2) ; extra == 'developing'
